RePoE/__init__.py
RePoE/poe_types.py
RePoE/data/active_skill_types.min.json
RePoE/data/atlas_tree.min.json
RePoE/data/base_items.min.json
RePoE/data/characters.min.json
RePoE/data/cluster_jewel_notables.min.json
RePoE/data/cluster_jewels.min.json
RePoE/data/cost_types.min.json
RePoE/data/crafting_bench_options.min.json
RePoE/data/default_monster_stats.min.json
RePoE/data/essences.min.json
RePoE/data/flavour.min.json
RePoE/data/fossils.min.json
RePoE/data/gem_tags.min.json
RePoE/data/gems.min.json
RePoE/data/item_classes.min.json
RePoE/data/mod_types.min.json
RePoE/data/mods.min.json
RePoE/data/skill_tree.min.json
RePoE/data/stat_translations.min.json
RePoE/data/stats.min.json
RePoE/data/tags.min.json
RePoE/wikidata/__init__.py
RePoE/wikidata/areas.min.json
RePoE/wikidata/atlas_maps.min.json
RePoE/wikidata/base_items.min.json
RePoE/wikidata/unique_items.min.json
RePoE/wikidata/unique_monsters.min.json
RePoE_Liberatorist-3.25.0.dist-info/LICENSE.md
RePoE_Liberatorist-3.25.0.dist-info/METADATA
RePoE_Liberatorist-3.25.0.dist-info/WHEEL
RePoE_Liberatorist-3.25.0.dist-info/top_level.txt
RePoE_Liberatorist-3.25.0.dist-info/RECORD
