Metadata-Version: 2.1
Name: RePoE-Liberatorist
Version: 3.25.0
Summary: Repository of Path of Exile resources for tool developers
Home-page: https://github.com/Liberatorist/RePoE
Author: Liberatorist
Author-email: 
License: proprietary
Requires-Python: >=3.11.0
License-File: LICENSE.md
